detective/__init__.py
detective/proto_utils.py
detective/snapshot.py
detective/tests/__init__.py
detective/tests/conftest.py
detective/tests/fixtures_data.py
detective/tests/test_snapshot.py
detective/tests/test_snapshot_exception_handling.py
detective/tests/test_snapshot_fields_selection.py
detective/tests/test_snapshot_function_nesting.py
detective/tests/utils.py
detective/tests/proto/cat_pb2.py
detective/tests/proto/generate_protos.py
detective_snapshot-0.1.16.dist-info/licenses/LICENSE
detective_snapshot-0.1.16.dist-info/METADATA
detective_snapshot-0.1.16.dist-info/WHEEL
detective_snapshot-0.1.16.dist-info/top_level.txt
detective_snapshot-0.1.16.dist-info/RECORD
