Metadata-Version: 2.4
Name: detective-snapshot
Version: 0.1.16
Summary: A Python package for capturing and comparing function input/output snapshots
Author-email: Caffeinated AI <caffeinated.ai.dev@gmail.com>
License: MIT License
Project-URL: Source Code, https://github.com/caffeinated-ai/detective-snapshot
Classifier: Development Status :: 3 - Alpha
Classifier: Intended Audience :: Developers
Classifier: License :: OSI Approved :: MIT License
Classifier: Operating System :: OS Independent
Classifier: Programming Language :: Python :: 3
Classifier: Programming Language :: Python :: 3.7
Classifier: Programming Language :: Python :: 3.8
Classifier: Programming Language :: Python :: 3.9
Classifier: Programming Language :: Python :: 3.10
Requires-Python: >=3.7
License-File: LICENSE
Requires-Dist: jsonpath-ng>=1.5.0
Requires-Dist: jsbeautifier>=1.14.0
Provides-Extra: proto
Requires-Dist: protobuf>=3.0.0; extra == "proto"
Provides-Extra: test
Requires-Dist: pytest>=7.0.0; extra == "test"
Requires-Dist: pytest-cov>=4.0.0; extra == "test"
Dynamic: license-file
